README.md
setup.py
vecino/__init__.py
vecino/__main__.py
vecino/repo2bow.py
vecino/similar_repositories.py
vecino.egg-info/PKG-INFO
vecino.egg-info/SOURCES.txt
vecino.egg-info/dependency_links.txt
vecino.egg-info/entry_points.txt
vecino.egg-info/requires.txt
vecino.egg-info/top_level.txt