Metadata-Version: 1.1
Name: vecino
Version: 0.2.0
Summary: Part of source{d}'s stack for machine learning on source code. Provides API and tools to find similar Git repositoriesbased on source code identifiers.
Home-page: https://github.com/src-d/vecino
Author: source{d}
Author-email: machine-learning@sourced.tech
License: Apache Software License
Download-URL: https://github.com/src-d/vecino
Keywords: machine learning on source code,word2vec,id2vec,github,swivel,nbow,bblfsh,babelfish,ast2vec
Platform: UNKNOWN
Classifier: Development Status :: 3 - Alpha
Classifier: Environment :: Console
Classifier: Intended Audience :: Developers
Classifier: License :: OSI Approved :: Apache Software License
Classifier: Operating System :: POSIX
Classifier: Programming Language :: Python :: 3.4
Classifier: Programming Language :: Python :: 3.5
Classifier: Programming Language :: Python :: 3.6
Classifier: Topic :: Software Development :: Libraries
